aimslib/__init__.py
aimslib/py.typed
aimslib/access/__init__.py
aimslib/access/brief_roster.py
aimslib/access/cache.py
aimslib/access/connect.py
aimslib/access/crew.py
aimslib/access/expanded_roster.py
aimslib/access/flightinfo.py
aimslib/access/trip.py
aimslib/common/__init__.py
aimslib/common/types.py
aimslib/detailed_roster/__init__.py
aimslib/detailed_roster/process.py
aimslib/output/__init__.py
aimslib/output/csv.py
aimslib/output/freeform.py
aimslib/output/ical.py
aimslib/output/roster.py
aimslib-0.4.post1.dist-info/LICENSE
aimslib-0.4.post1.dist-info/METADATA
aimslib-0.4.post1.dist-info/WHEEL
aimslib-0.4.post1.dist-info/top_level.txt
aimslib-0.4.post1.dist-info/RECORD
