Metadata-Version: 2.1
Name: aimslib
Version: 0.4.post1
Summary: A library for working with AIMS
Home-page: https://github.com/JonHurst/aimslib
Author: Jon Hurst
Author-email: jon.a@hursts.org.uk
License: UNKNOWN
Platform: UNKNOWN
Classifier: Development Status :: 3 - Alpha
Classifier: Programming Language :: Python :: 3
Classifier: License :: OSI Approved :: GNU General Public License v3 or later (GPLv3+)
Classifier: Operating System :: OS Independent
Requires-Python: >=3.7
License-File: LICENSE
Requires-Dist: Beautifulsoup4
Requires-Dist: requests
Requires-Dist: python-dateutil
Requires-Dist: nightflight
